exactly_lib/__init__.py
exactly_lib/program_info.py
exactly_lib/cli/__init__.py
exactly_lib/cli/builtin_symbol.py
exactly_lib/cli/custom_symbol.py
exactly_lib/cli/main_program.py
exactly_lib/cli/test_case_def.py
exactly_lib/cli/test_suite_def.py
exactly_lib/cli/definitions/__init__.py
exactly_lib/cli/definitions/common_cli_options.py
exactly_lib/cli/definitions/exit_codes.py
exactly_lib/cli/definitions/program_modes/__init__.py
exactly_lib/cli/definitions/program_modes/help/__init__.py
exactly_lib/cli/definitions/program_modes/help/arguments_for.py
exactly_lib/cli/definitions/program_modes/help/command_line_options.py
exactly_lib/cli/definitions/program_modes/symbol/__init__.py
exactly_lib/cli/definitions/program_modes/symbol/command_line_options.py
exactly_lib/cli/definitions/program_modes/test_case/__init__.py
exactly_lib/cli/definitions/program_modes/test_case/command_line_options.py
exactly_lib/cli/definitions/program_modes/test_suite/__init__.py
exactly_lib/cli/definitions/program_modes/test_suite/command_line_options.py
exactly_lib/cli/program_modes/__init__.py
exactly_lib/cli/program_modes/common/__init__.py
exactly_lib/cli/program_modes/common/argument_parsing_of_actor.py
exactly_lib/cli/program_modes/common/shlex_arg_parse.py
exactly_lib/cli/program_modes/help/__init__.py
exactly_lib/cli/program_modes/help/argument_parsing.py
exactly_lib/cli/program_modes/help/entities_requests.py
exactly_lib/cli/program_modes/help/error.py
exactly_lib/cli/program_modes/help/html_doc/__init__.py
exactly_lib/cli/program_modes/help/html_doc/help_request.py
exactly_lib/cli/program_modes/help/html_doc/request_rendering.py
exactly_lib/cli/program_modes/help/program_modes/__init__.py
exactly_lib/cli/program_modes/help/program_modes/help_request.py
exactly_lib/cli/program_modes/help/program_modes/utils.py
exactly_lib/cli/program_modes/help/program_modes/main_program/__init__.py
exactly_lib/cli/program_modes/help/program_modes/main_program/help_request.py
exactly-0.15.0.dist-info/LICENSE
exactly-0.15.0.dist-info/METADATA
exactly-0.15.0.dist-info/WHEEL
exactly-0.15.0.dist-info/entry_points.txt
exactly-0.15.0.dist-info/top_level.txt
exactly-0.15.0.dist-info/RECORD
