Metadata-Version: 2.1
Name: exactly
Version: 0.15.0
Summary: Tests a command line program by executing it in a temporary sandbox directory and inspecting its result.
Home-page: https://github.com/emilkarlen/exactly
Author: Emil Karlen
Author-email: emil@member.fsf.org
License: GPLv3+
Keywords: test case suite check assert script shell console command line program execute sandbox
Platform: UNKNOWN
Classifier: Development Status :: 5 - Production/Stable
Classifier: Programming Language :: Python :: 3
Classifier: Programming Language :: Python :: 3.6
Classifier: Programming Language :: Python :: 3.7
Classifier: Programming Language :: Python :: 3.8
Classifier: Programming Language :: Python :: 3.9
Classifier: License :: OSI Approved :: GNU General Public License v3 or later (GPLv3+)
Classifier: Topic :: Software Development :: Testing
Classifier: Topic :: System :: Systems Administration
Classifier: Environment :: Console
Classifier: Operating System :: POSIX
Requires-Python: >=3.6
